pyconfbox/__init__.py
pyconfbox/py.typed
pyconfbox/core/__init__.py
pyconfbox/core/config.py
pyconfbox/core/exceptions.py
pyconfbox/core/immutable.py
pyconfbox/core/types.py
pyconfbox/plugins/__init__.py
pyconfbox/storage/__init__.py
pyconfbox/storage/base.py
pyconfbox/storage/environment.py
pyconfbox/storage/file.py
pyconfbox/storage/memory.py
pyconfbox/storage/redis.py
pyconfbox/storage/sqlite.py
pyconfbox/utils/__init__.py
pyconfbox-0.1.2.dist-info/METADATA
pyconfbox-0.1.2.dist-info/WHEEL
pyconfbox-0.1.2.dist-info/licenses/LICENSE
pyconfbox-0.1.2.dist-info/RECORD
