Metadata-Version: 2.4
Name: pyconfbox
Version: 0.1.2
Summary: Unified configuration management system for Python applications with multiple storage backends, type validation, and immutability control
Project-URL: Homepage, https://github.com/dan1901/pyconfbox
Project-URL: Documentation, https://github.com/dan1901/pyconfbox/tree/main/docs
Project-URL: Documentation (English), https://github.com/dan1901/pyconfbox/tree/main/docs/en
Project-URL: Documentation (한국어), https://github.com/dan1901/pyconfbox/tree/main/docs/ko
Project-URL: Repository, https://github.com/dan1901/pyconfbox
Project-URL: Issues, https://github.com/dan1901/pyconfbox/issues
Project-URL: Changelog, https://github.com/dan1901/pyconfbox/releases
Author-email: Gabriel Ki <edc1901@gmail.com>
License: MIT License
License-File: LICENSE
Keywords: config,configuration,django,environment,settings,storage,variables
Classifier: Development Status :: 4 - Beta
Classifier: Intended Audience :: Developers
Classifier: License :: OSI Approved :: MIT License
Classifier: Programming Language :: Python :: 3
Classifier: Programming Language :: Python :: 3.8
Classifier: Programming Language :: Python :: 3.9
Classifier: Programming Language :: Python :: 3.10
Classifier: Programming Language :: Python :: 3.11
Classifier: Programming Language :: Python :: 3.12
Classifier: Programming Language :: Python :: 3.13
Classifier: Topic :: Software Development :: Libraries :: Python Modules
Classifier: Topic :: System :: Systems Administration
Classifier: Topic :: Utilities
Requires-Python: >=3.8
Requires-Dist: pydantic>=2.0.0
Provides-Extra: all
Requires-Dist: cryptography>=41.0.0; extra == 'all'
Requires-Dist: pyyaml>=6.0; extra == 'all'
Requires-Dist: redis>=5.0.0; extra == 'all'
Requires-Dist: toml>=0.10.0; extra == 'all'
Provides-Extra: crypto
Requires-Dist: cryptography>=41.0.0; extra == 'crypto'
Provides-Extra: file-formats
Requires-Dist: pyyaml>=6.0; extra == 'file-formats'
Requires-Dist: toml>=0.10.0; extra == 'file-formats'
Provides-Extra: redis
Requires-Dist: redis>=5.0.0; extra == 'redis'
Provides-Extra: toml
Requires-Dist: toml>=0.10.0; extra == 'toml'
Provides-Extra: yaml
Requires-Dist: pyyaml>=6.0; extra == 'yaml'
